wagtail_seo-3.1.1.dist-info/licenses/LICENSE.txt
wagtailseo/__init__.py
wagtailseo/apps.py
wagtailseo/blocks.py
wagtailseo/models.py
wagtailseo/schema.py
wagtailseo/settings.py
wagtailseo/utils.py
wagtailseo/wagtail_hooks.py
wagtailseo/migrations/0001_initial.py
wagtailseo/migrations/0002_remove_seosettings_amp_pages.py
wagtailseo/migrations/0003_seosettings_struct_org_fields.py
wagtailseo/migrations/0004_seosettings_og_image_default.py
wagtailseo/migrations/__init__.py
wagtailseo/templates/wagtailseo/meta.html
wagtailseo/templates/wagtailseo/search-preview.html
wagtailseo/templates/wagtailseo/struct_data.html
wagtailseo/templates/wagtailseo/struct_org_data.html
wagtailseo/templates/wagtailseo/wagtailseo-line-chart.svg
wagtail_seo-3.1.1.dist-info/METADATA
wagtail_seo-3.1.1.dist-info/WHEEL
wagtail_seo-3.1.1.dist-info/top_level.txt
wagtail_seo-3.1.1.dist-info/RECORD
