Metadata-Version: 2.4
Name: wagtail-seo
Version: 3.1.1
Summary: Search engine and social media optimization for Wagtail.
Author-email: CodeRed LLC <info@coderedcorp.com>
License: BSD 3-Clause License
Project-URL: Source, https://github.com/coderedcorp/wagtail-seo
Project-URL: Documentation, https://docs.coderedcorp.com/wagtail-seo/
Project-URL: Changelog, https://docs.coderedcorp.com/wagtail-seo/releases.html
Classifier: Framework :: Django
Classifier: Framework :: Wagtail
Classifier: Framework :: Wagtail :: 4
Classifier: Framework :: Wagtail :: 5
Classifier: Framework :: Wagtail :: 6
Classifier: Framework :: Wagtail :: 7
Classifier: Intended Audience :: Developers
Classifier: License :: OSI Approved :: BSD License
Classifier: Natural Language :: English
Classifier: Operating System :: OS Independent
Classifier: Programming Language :: Python :: 3
Classifier: Programming Language :: Python :: 3 :: Only
Classifier: Topic :: Internet :: WWW/HTTP :: Site Management
Requires-Python: >=3.9
License-File: LICENSE.txt
Requires-Dist: wagtail<8.0,>=4.0
Dynamic: license-file
